[{"line":1,"elements":[{"start_timestamp":"2026-02-03T12:35:18.158Z","before":[{"result":{"duration":7526210000,"status":"passed"},"match":{"location":"hooks.Hooks.setup()"}}],"line":7,"name":"Verify OpenCart home page launch","description":"","id":"opencart-e-commerce-end-to-end-automation;verify-opencart-home-page-launch","after":[{"result":{"duration":405028800,"status":"passed"},"match":{"location":"hooks.Hooks.tearDown(io.cucumber.java.Scenario)"}}],"type":"scenario","keyword":"Scenario","steps":[{"result":{"duration":199760300,"status":"passed"},"line":8,"name":"user launches the application","match":{"location":"stepdefinitions.E2ESteps.user_launches_the_application()"},"keyword":"Given "},{"result":{"duration":145148600,"status":"passed"},"line":9,"name":"home page should be displayed successfully","match":{"location":"stepdefinitions.E2ESteps.home_page_should_be_displayed_successfully()"},"keyword":"Then "}],"tags":[{"name":"@Smoke"}]},{"start_timestamp":"2026-02-03T12:35:26.705Z","before":[{"result":{"duration":3356366400,"status":"passed"},"match":{"location":"hooks.Hooks.setup()"}}],"line":14,"name":"Search product and add to cart","description":"","id":"opencart-e-commerce-end-to-end-automation;search-product-and-add-to-cart","after":[{"result":{"duration":440243300,"status":"passed"},"match":{"location":"hooks.Hooks.tearDown(io.cucumber.java.Scenario)"}}],"type":"scenario","keyword":"Scenario","steps":[{"result":{"duration":107657800,"status":"passed"},"line":15,"name":"user launches the application","match":{"location":"stepdefinitions.E2ESteps.user_launches_the_application()"},"keyword":"Given "},{"result":{"duration":643969400,"status":"passed"},"line":16,"name":"user searches for product \"MacBook\"","match":{"arguments":[{"val":"\"MacBook\"","offset":26}],"location":"stepdefinitions.E2ESteps.user_searches_for_product(java.lang.String)"},"keyword":"When "},{"result":{"duration":3064853000,"status":"passed"},"line":17,"name":"user selects the product and adds to cart","match":{"location":"stepdefinitions.E2ESteps.user_selects_the_product_and_adds_to_cart()"},"keyword":"And "},{"result":{"duration":646448700,"status":"passed"},"line":18,"name":"product should be added to cart successfully","match":{"location":"stepdefinitions.E2ESteps.product_should_be_added_to_cart_successfully()"},"keyword":"Then "}],"tags":[{"name":"@Regression"}]},{"start_timestamp":"2026-02-03T12:35:35.016Z","before":[{"result":{"duration":4661707700,"status":"passed"},"match":{"location":"hooks.Hooks.setup()"}}],"line":23,"name":"Validate cart and remove product","description":"","id":"opencart-e-commerce-end-to-end-automation;validate-cart-and-remove-product","after":[{"result":{"duration":614892300,"status":"passed"},"match":{"location":"hooks.Hooks.tearDown(io.cucumber.java.Scenario)"}}],"type":"scenario","keyword":"Scenario","steps":[{"result":{"duration":133576400,"status":"passed"},"line":24,"name":"user launches the application","match":{"location":"stepdefinitions.E2ESteps.user_launches_the_application()"},"keyword":"Given "},{"result":{"duration":630317800,"status":"passed"},"line":25,"name":"user searches for product \"MacBook\"","match":{"arguments":[{"val":"\"MacBook\"","offset":26}],"location":"stepdefinitions.E2ESteps.user_searches_for_product(java.lang.String)"},"keyword":"When "},{"result":{"duration":2875216400,"status":"passed"},"line":26,"name":"user selects the product and adds to cart","match":{"location":"stepdefinitions.E2ESteps.user_selects_the_product_and_adds_to_cart()"},"keyword":"And "},{"result":{"duration":1405899200,"status":"passed"},"line":27,"name":"user navigates to cart page","match":{"location":"stepdefinitions.E2ESteps.user_navigates_to_cart_page()"},"keyword":"And "},{"result":{"duration":553219900,"status":"passed"},"line":28,"name":"user removes the product from cart","match":{"location":"stepdefinitions.E2ESteps.user_removes_the_product_from_cart()"},"keyword":"And "},{"result":{"duration":3826189800,"status":"passed"},"line":29,"name":"cart should be empty","match":{"location":"stepdefinitions.E2ESteps.cart_should_be_empty()"},"keyword":"Then "}],"tags":[{"name":"@Integration"}]},{"start_timestamp":"2026-02-03T12:35:49.754Z","before":[{"result":{"duration":2985453800,"status":"passed"},"match":{"location":"hooks.Hooks.setup()"}}],"line":34,"name":"Complete end-to-end purchase flow","description":"","id":"opencart-e-commerce-end-to-end-automation;complete-end-to-end-purchase-flow","after":[{"result":{"duration":237343000,"status":"passed"},"match":{"location":"hooks.Hooks.tearDown(io.cucumber.java.Scenario)"}}],"type":"scenario","keyword":"Scenario","steps":[{"result":{"duration":73902800,"status":"passed"},"line":35,"name":"user launches the application","match":{"location":"stepdefinitions.E2ESteps.user_launches_the_application()"},"keyword":"Given "},{"result":{"duration":703527700,"status":"passed"},"line":36,"name":"user searches for product \"MacBook\"","match":{"arguments":[{"val":"\"MacBook\"","offset":26}],"location":"stepdefinitions.E2ESteps.user_searches_for_product(java.lang.String)"},"keyword":"When "},{"result":{"duration":2726698500,"status":"passed"},"line":37,"name":"user selects the product and adds to cart","match":{"location":"stepdefinitions.E2ESteps.user_selects_the_product_and_adds_to_cart()"},"keyword":"And "},{"result":{"duration":1365375800,"status":"passed"},"line":38,"name":"user navigates to cart page","match":{"location":"stepdefinitions.E2ESteps.user_navigates_to_cart_page()"},"keyword":"And "},{"result":{"duration":1737602000,"status":"passed"},"line":39,"name":"user proceeds to checkout","match":{"location":"stepdefinitions.E2ESteps.user_proceeds_to_checkout()"},"keyword":"And "},{"result":{"duration":77118600,"status":"passed"},"line":40,"name":"checkout page should be displayed","match":{"location":"stepdefinitions.E2ESteps.checkout_page_should_be_displayed()"},"keyword":"Then "}],"tags":[{"name":"@E2E"}]},{"start_timestamp":"2026-02-03T12:35:59.685Z","before":[{"result":{"duration":2542648600,"status":"passed"},"match":{"location":"hooks.Hooks.setup()"}}],"line":45,"name":"Login with invalid credentials","description":"","id":"opencart-e-commerce-end-to-end-automation;login-with-invalid-credentials","after":[{"result":{"duration":326220400,"status":"passed"},"match":{"location":"hooks.Hooks.tearDown(io.cucumber.java.Scenario)"}}],"type":"scenario","keyword":"Scenario","steps":[{"result":{"duration":83998100,"status":"passed"},"line":46,"name":"user launches the application","match":{"location":"stepdefinitions.E2ESteps.user_launches_the_application()"},"keyword":"Given "},{"result":{"duration":1377687800,"status":"passed"},"line":47,"name":"user navigates to login page","match":{"location":"stepdefinitions.E2ESteps.user_navigates_to_login_page()"},"keyword":"When "},{"result":{"duration":1469815400,"status":"passed"},"line":48,"name":"user logs in with username \"fake@mail.com\" and password \"wrong123\"","match":{"arguments":[{"val":"\"fake@mail.com\"","offset":27},{"val":"\"wrong123\"","offset":56}],"location":"stepdefinitions.E2ESteps.user_logs_in_with_username_and_password(java.lang.String,java.lang.String)"},"keyword":"And "},{"result":{"duration":627651400,"status":"passed"},"line":49,"name":"warning message should be displayed","match":{"location":"stepdefinitions.E2ESteps.warning_message_should_be_displayed()"},"keyword":"Then "}],"tags":[{"name":"@Negative"}]}],"name":"OpenCart E-Commerce End-to-End Automation","description":"  This feature validates smoke, regression, integration,\n  negative, and end-to-end scenarios for OpenCart application","id":"opencart-e-commerce-end-to-end-automation","keyword":"Feature","uri":"classpath:features/Ecommerce.feature","tags":[]}]